buildbot_mattermost/__init__.py
buildbot_mattermost/reporter.py
buildbot_mattermost_reporter-0.2.0.dist-info/LICENSE
buildbot_mattermost_reporter-0.2.0.dist-info/METADATA
buildbot_mattermost_reporter-0.2.0.dist-info/WHEEL
buildbot_mattermost_reporter-0.2.0.dist-info/entry_points.txt
buildbot_mattermost_reporter-0.2.0.dist-info/top_level.txt
buildbot_mattermost_reporter-0.2.0.dist-info/RECORD
