Metadata-Version: 2.1
Name: buildbot-mattermost-reporter
Version: 0.2.0
Summary: Mattermost status reporter for Buildbot
Author-email: Aksel Sjögren <sjoegren@mailc.net>
Project-URL: Homepage, https://github.com/sjoegren/buildbot-mattermost-reporter
Project-URL: Issues, https://github.com/sjoegren/buildbot-mattermost-reporter/issues
Classifier: Development Status :: 3 - Alpha
Classifier: Environment :: Plugins
Classifier: Intended Audience :: Developers
Classifier: License :: OSI Approved :: MIT License
Classifier: Operating System :: OS Independent
Classifier: Programming Language :: Python :: 3
Classifier: Topic :: Software Development :: Build Tools
Requires-Python: >=3.8
License-File: LICENSE
Requires-Dist: buildbot >=3.0
Provides-Extra: test
Requires-Dist: black ; extra == 'test'
Requires-Dist: flake8 ; extra == 'test'
Requires-Dist: pytest ; extra == 'test'
Requires-Dist: pytest-mock ; extra == 'test'
Requires-Dist: txrequests ; extra == 'test'
